hydrogym/__init__.py
hydrogym/core.py
hydrogym/distributed/__init__.py
hydrogym/firedrake/__init__.py
hydrogym/firedrake/actuator.py
hydrogym/firedrake/envs/__init__.py
hydrogym/firedrake/envs/cavity/__init__.py
hydrogym/firedrake/envs/cavity/coarse.geo
hydrogym/firedrake/envs/cavity/coarse.msh
hydrogym/firedrake/envs/cavity/fine.geo
hydrogym/firedrake/envs/cavity/fine.msh
hydrogym/firedrake/envs/cavity/flow.py
hydrogym/firedrake/envs/cavity/medium.geo
hydrogym/firedrake/envs/cavity/medium.msh
hydrogym/firedrake/envs/cylinder/__init__.py
hydrogym/firedrake/envs/cylinder/coarse.geo
hydrogym/firedrake/envs/cylinder/coarse.msh
hydrogym/firedrake/envs/cylinder/fine.geo
hydrogym/firedrake/envs/cylinder/fine.msh
hydrogym/firedrake/envs/cylinder/flow.py
hydrogym/firedrake/envs/cylinder/medium.geo
hydrogym/firedrake/envs/cylinder/medium.msh
hydrogym/firedrake/envs/pinball/__init__.py
hydrogym/firedrake/envs/pinball/coarse.geo
hydrogym/firedrake/envs/pinball/coarse.msh
hydrogym/firedrake/envs/pinball/fine.geo
hydrogym/firedrake/envs/pinball/fine.msh
hydrogym/firedrake/envs/pinball/flow.py
hydrogym/firedrake/envs/step/__init__.py
hydrogym/firedrake/envs/step/coarse.geo
hydrogym/firedrake/envs/step/coarse.msh
hydrogym/firedrake/envs/step/fine.geo
hydrogym/firedrake/envs/step/fine.msh
hydrogym/firedrake/envs/step/flow.py
hydrogym/firedrake/envs/step/medium.geo
hydrogym/firedrake/envs/step/medium.msh
hydrogym/firedrake/flow.py
hydrogym/firedrake/solver.py
hydrogym/firedrake/utils/__init__.py
hydrogym/firedrake/utils/io.py
hydrogym/firedrake/utils/linalg.py
hydrogym/firedrake/utils/modeling.py
hydrogym/firedrake/utils/modred_interface.py
hydrogym/firedrake/utils/utils.py
hydrogym-0.1.2.1.dist-info/METADATA
hydrogym-0.1.2.1.dist-info/LICENSE
hydrogym-0.1.2.1.dist-info/WHEEL
hydrogym-0.1.2.1.dist-info/RECORD
