Metadata-Version: 2.1
Name: hydrogym
Version: 0.1.2.1
Summary: A Reinforcement Learning Benchmarking Environment for Fluid Dynamics
Home-page: https://github.com/dynamicslab/hydrogym
License: MIT
Keywords: Reinforcement Learning,Scientific Machine Learning,Benchmarking,Computational Fluid Dynamics
Author: Jared Callaham et al.
Maintainer: Jared Callaham
Maintainer-email: jared.callaham@gmail.com
Requires-Python: >=3.8,<4.0
Classifier: Development Status :: 2 - Pre-Alpha
Classifier: Intended Audience :: Science/Research
Classifier: License :: OSI Approved :: MIT License
Classifier: Operating System :: MacOS
Classifier: Operating System :: Unix
Classifier: Programming Language :: Python
Classifier: Programming Language :: Python :: 3
Classifier: Programming Language :: Python :: 3.8
Classifier: Programming Language :: Python :: 3.9
Classifier: Programming Language :: Python :: 3.10
Classifier: Programming Language :: Python :: 3.11
Classifier: Programming Language :: Python :: 3
Classifier: Programming Language :: Python :: 3.10
Classifier: Programming Language :: Python :: 3.11
Classifier: Programming Language :: Python :: 3.8
Classifier: Programming Language :: Python :: 3.9
Classifier: Topic :: Scientific/Engineering :: Artificial Intelligence
Classifier: Topic :: Scientific/Engineering :: Atmospheric Science
Classifier: Topic :: Scientific/Engineering :: Hydrology
Classifier: Topic :: Scientific/Engineering :: Physics
Requires-Dist: control (>=0.9.2,<0.10.0)
Requires-Dist: dmsuite (>=0.1.1,<0.2.0)
Requires-Dist: evotorch (>=0.3.0,<0.4.0)
Requires-Dist: gmsh (>=4.11.1,<5.0.0)
Requires-Dist: gym (>=0.26.2,<0.27.0)
Requires-Dist: modred (>=2.1.0,<3.0.0)
Requires-Dist: torch (==1.13)
Project-URL: Documentation, https://hydrogym.readthedocs.io/
Project-URL: Repository, https://github.com/dynamicslab/hydrogym
Project-URL: issues, https://github.com/dynamicslab/hydrogym/issues
